{"nodes": [{"id": "dukan_x_lib_core_billing_dunning_service_dart", "label": "dunning_service.dart", "file_type": "code", "source_file": "Dukan_x\\lib\\core\\billing\\dunning_service.dart", "source_location": null}, {"id": "dukan_x_lib_core_billing_dunning_service_dart_dunningservice", "label": "DunningService", "file_type": "code", "source_file": "Dukan_x\\lib\\core\\billing\\dunning_service.dart", "source_location": null}, {"id": "package_drift_drift_dart", "label": "package:drift/drift.dart", "file_type": "code", "source_file": "Dukan_x\\lib\\core\\billing\\dunning_service.dart", "source_location": null}, {"id": "package_uuid_uuid_dart", "label": "package:uuid/uuid.dart", "file_type": "code", "source_file": "Dukan_x\\lib\\core\\billing\\dunning_service.dart", "source_location": null}, {"id": "database_app_database_dart", "label": "../database/app_database.dart", "file_type": "code", "source_file": "Dukan_x\\lib\\core\\billing\\dunning_service.dart", "source_location": null}, {"id": "repository_bills_repository_dart", "label": "../repository/bills_repository.dart", "file_type": "code", "source_file": "Dukan_x\\lib\\core\\billing\\dunning_service.dart", "source_location": null}, {"id": "repository_customers_repository_dart", "label": "../repository/customers_repository.dart", "file_type": "code", "source_file": "Dukan_x\\lib\\core\\billing\\dunning_service.dart", "source_location": null}, {"id": "features_marketing_data_services_whatsapp_service_dart", "label": "../../features/marketing/data/services/whatsapp_service.dart", "file_type": "code", "source_file": "Dukan_x\\lib\\core\\billing\\dunning_service.dart", "source_location": null}], "edges": [{"source": "dukan_x_lib_core_billing_dunning_service_dart", "target": "dukan_x_lib_core_billing_dunning_service_dart_dunningservice", "relation": "defines", "confidence": "EXTRACTED", "confidence_score": 1.0, "source_file": "Dukan_x\\lib\\core\\billing\\dunning_service.dart", "source_location": null, "weight": 1.0}, {"source": "dukan_x_lib_core_billing_dunning_service_dart", "target": "package_drift_drift_dart", "relation": "imports", "confidence": "EXTRACTED", "confidence_score": 1.0, "source_file": "Dukan_x\\lib\\core\\billing\\dunning_service.dart", "source_location": null, "weight": 1.0}, {"source": "dukan_x_lib_core_billing_dunning_service_dart", "target": "package_uuid_uuid_dart", "relation": "imports", "confidence": "EXTRACTED", "confidence_score": 1.0, "source_file": "Dukan_x\\lib\\core\\billing\\dunning_service.dart", "source_location": null, "weight": 1.0}, {"source": "dukan_x_lib_core_billing_dunning_service_dart", "target": "database_app_database_dart", "relation": "imports", "confidence": "EXTRACTED", "confidence_score": 1.0, "source_file": "Dukan_x\\lib\\core\\billing\\dunning_service.dart", "source_location": null, "weight": 1.0}, {"source": "dukan_x_lib_core_billing_dunning_service_dart", "target": "repository_bills_repository_dart", "relation": "imports", "confidence": "EXTRACTED", "confidence_score": 1.0, "source_file": "Dukan_x\\lib\\core\\billing\\dunning_service.dart", "source_location": null, "weight": 1.0}, {"source": "dukan_x_lib_core_billing_dunning_service_dart", "target": "repository_customers_repository_dart", "relation": "imports", "confidence": "EXTRACTED", "confidence_score": 1.0, "source_file": "Dukan_x\\lib\\core\\billing\\dunning_service.dart", "source_location": null, "weight": 1.0}, {"source": "dukan_x_lib_core_billing_dunning_service_dart", "target": "features_marketing_data_services_whatsapp_service_dart", "relation": "imports", "confidence": "EXTRACTED", "confidence_score": 1.0, "source_file": "Dukan_x\\lib\\core\\billing\\dunning_service.dart", "source_location": null, "weight": 1.0}]}