{"nodes": [{"id": "dukan_x_lib_features_shared_charts_sparkline_widget_dart", "label": "sparkline_widget.dart", "file_type": "code", "source_file": "Dukan_x\\lib\\features\\shared\\charts\\sparkline_widget.dart", "source_location": null}, {"id": "dukan_x_lib_features_shared_charts_sparkline_widget_dart_sparklinewidget", "label": "SparklineWidget", "file_type": "code", "source_file": "Dukan_x\\lib\\features\\shared\\charts\\sparkline_widget.dart", "source_location": null}, {"id": "dukan_x_lib_features_shared_charts_sparkline_widget_dart_build", "label": "build", "file_type": "code", "source_file": "Dukan_x\\lib\\features\\shared\\charts\\sparkline_widget.dart", "source_location": null}, {"id": "dukan_x_lib_features_shared_charts_sparkline_widget_dart_sizedbox", "label": "SizedBox", "file_type": "code", "source_file": "Dukan_x\\lib\\features\\shared\\charts\\sparkline_widget.dart", "source_location": null}, {"id": "package_fl_chart_fl_chart_dart", "label": "package:fl_chart/fl_chart.dart", "file_type": "code", "source_file": "Dukan_x\\lib\\features\\shared\\charts\\sparkline_widget.dart", "source_location": null}, {"id": "package_flutter_material_dart", "label": "package:flutter/material.dart", "file_type": "code", "source_file": "Dukan_x\\lib\\features\\shared\\charts\\sparkline_widget.dart", "source_location": null}], "edges": [{"source": "dukan_x_lib_features_shared_charts_sparkline_widget_dart", "target": "dukan_x_lib_features_shared_charts_sparkline_widget_dart_sparklinewidget", "relation": "defines", "confidence": "EXTRACTED", "confidence_score": 1.0, "source_file": "Dukan_x\\lib\\features\\shared\\charts\\sparkline_widget.dart", "source_location": null, "weight": 1.0}, {"source": "dukan_x_lib_features_shared_charts_sparkline_widget_dart", "target": "dukan_x_lib_features_shared_charts_sparkline_widget_dart_build", "relation": "defines", "confidence": "EXTRACTED", "confidence_score": 1.0, "source_file": "Dukan_x\\lib\\features\\shared\\charts\\sparkline_widget.dart", "source_location": null, "weight": 1.0}, {"source": "dukan_x_lib_features_shared_charts_sparkline_widget_dart", "target": "dukan_x_lib_features_shared_charts_sparkline_widget_dart_sizedbox", "relation": "defines", "confidence": "EXTRACTED", "confidence_score": 1.0, "source_file": "Dukan_x\\lib\\features\\shared\\charts\\sparkline_widget.dart", "source_location": null, "weight": 1.0}, {"source": "dukan_x_lib_features_shared_charts_sparkline_widget_dart", "target": "package_fl_chart_fl_chart_dart", "relation": "imports", "confidence": "EXTRACTED", "confidence_score": 1.0, "source_file": "Dukan_x\\lib\\features\\shared\\charts\\sparkline_widget.dart", "source_location": null, "weight": 1.0}, {"source": "dukan_x_lib_features_shared_charts_sparkline_widget_dart", "target": "package_flutter_material_dart", "relation": "imports", "confidence": "EXTRACTED", "confidence_score": 1.0, "source_file": "Dukan_x\\lib\\features\\shared\\charts\\sparkline_widget.dart", "source_location": null, "weight": 1.0}]}