{"nodes": [{"id": "dukan_x_my_backend_src_handlers_legacy_compat_ts", "label": "legacy-compat.ts", "file_type": "code", "source_file": "Dukan_x\\my-backend\\src\\handlers\\legacy-compat.ts", "source_location": "L1"}, {"id": "legacy_compat_parsejsonbody", "label": "parseJsonBody()", "file_type": "code", "source_file": "Dukan_x\\my-backend\\src\\handlers\\legacy-compat.ts", "source_location": "L7"}, {"id": "legacy_compat_mapuserprofile", "label": "mapUserProfile()", "file_type": "code", "source_file": "Dukan_x\\my-backend\\src\\handlers\\legacy-compat.ts", "source_location": "L16"}], "edges": [{"source": "dukan_x_my_backend_src_handlers_legacy_compat_ts", "target": "crypto", "relation": "imports_from", "confidence": "EXTRACTED", "source_file": "Dukan_x\\my-backend\\src\\handlers\\legacy-compat.ts", "source_location": "L1", "weight": 1.0}, {"source": "dukan_x_my_backend_src_handlers_legacy_compat_ts", "target": "dukan_x_my_backend_src_middleware_handler_wrapper", "relation": "imports_from", "confidence": "EXTRACTED", "source_file": "Dukan_x\\my-backend\\src\\handlers\\legacy-compat.ts", "source_location": "L2", "weight": 1.0}, {"source": "dukan_x_my_backend_src_handlers_legacy_compat_ts", "target": "dukan_x_my_backend_src_types_tenant_types", "relation": "imports_from", "confidence": "EXTRACTED", "source_file": "Dukan_x\\my-backend\\src\\handlers\\legacy-compat.ts", "source_location": "L3", "weight": 1.0}, {"source": "dukan_x_my_backend_src_handlers_legacy_compat_ts", "target": "dukan_x_my_backend_src_config_dynamodb_config", "relation": "imports_from", "confidence": "EXTRACTED", "source_file": "Dukan_x\\my-backend\\src\\handlers\\legacy-compat.ts", "source_location": "L4", "weight": 1.0}, {"source": "dukan_x_my_backend_src_handlers_legacy_compat_ts", "target": "dukan_x_my_backend_src_utils_response", "relation": "imports_from", "confidence": "EXTRACTED", "source_file": "Dukan_x\\my-backend\\src\\handlers\\legacy-compat.ts", "source_location": "L5", "weight": 1.0}, {"source": "dukan_x_my_backend_src_handlers_legacy_compat_ts", "target": "legacy_compat_parsejsonbody", "relation": "contains", "confidence": "EXTRACTED", "source_file": "Dukan_x\\my-backend\\src\\handlers\\legacy-compat.ts", "source_location": "L7", "weight": 1.0}, {"source": "dukan_x_my_backend_src_handlers_legacy_compat_ts", "target": "legacy_compat_mapuserprofile", "relation": "contains", "confidence": "EXTRACTED", "source_file": "Dukan_x\\my-backend\\src\\handlers\\legacy-compat.ts", "source_location": "L16", "weight": 1.0}], "raw_calls": [{"caller_nid": "legacy_compat_parsejsonbody", "callee": "parse", "source_file": "Dukan_x\\my-backend\\src\\handlers\\legacy-compat.ts", "source_location": "L10"}]}