{"nodes": [{"id": "dukan_x_my_backend_src_services_dashboard_analytics_service_ts", "label": "dashboard-analytics.service.ts", "file_type": "code", "source_file": "Dukan_x\\my-backend\\src\\services\\dashboard-analytics.service.ts", "source_location": "L1"}, {"id": "dashboard_analytics_service_todayrange", "label": "toDayRange()", "file_type": "code", "source_file": "Dukan_x\\my-backend\\src\\services\\dashboard-analytics.service.ts", "source_location": "L12"}, {"id": "dashboard_analytics_service_tomonthstart", "label": "toMonthStart()", "file_type": "code", "source_file": "Dukan_x\\my-backend\\src\\services\\dashboard-analytics.service.ts", "source_location": "L23"}, {"id": "dashboard_analytics_service_tomonthkey", "label": "toMonthKey()", "file_type": "code", "source_file": "Dukan_x\\my-backend\\src\\services\\dashboard-analytics.service.ts", "source_location": "L27"}, {"id": "dashboard_analytics_service_isactiveinvoice", "label": "isActiveInvoice()", "file_type": "code", "source_file": "Dukan_x\\my-backend\\src\\services\\dashboard-analytics.service.ts", "source_location": "L31"}, {"id": "dashboard_analytics_service_toamount", "label": "toAmount()", "file_type": "code", "source_file": "Dukan_x\\my-backend\\src\\services\\dashboard-analytics.service.ts", "source_location": "L37"}, {"id": "dashboard_analytics_service_fetchinvoicesinrange", "label": "fetchInvoicesInRange()", "file_type": "code", "source_file": "Dukan_x\\my-backend\\src\\services\\dashboard-analytics.service.ts", "source_location": "L42"}, {"id": "dashboard_analytics_service_fetchallactiveinvoices", "label": "fetchAllActiveInvoices()", "file_type": "code", "source_file": "Dukan_x\\my-backend\\src\\services\\dashboard-analytics.service.ts", "source_location": "L55"}, {"id": "dashboard_analytics_service_dashboardanalyticsservice", "label": "DashboardAnalyticsService", "file_type": "code", "source_file": "Dukan_x\\my-backend\\src\\services\\dashboard-analytics.service.ts", "source_location": "L63"}, {"id": "dashboard_analytics_service_dashboardanalyticsservice_getdashboardsummary", "label": ".getDashboardSummary()", "file_type": "code", "source_file": "Dukan_x\\my-backend\\src\\services\\dashboard-analytics.service.ts", "source_location": "L64"}, {"id": "dashboard_analytics_service_dashboardanalyticsservice_getsalestrend", "label": ".getSalesTrend()", "file_type": "code", "source_file": "Dukan_x\\my-backend\\src\\services\\dashboard-analytics.service.ts", "source_location": "L108"}, {"id": "dashboard_analytics_service_dashboardanalyticsservice_getrevenuemonthly", "label": ".getRevenueMonthly()", "file_type": "code", "source_file": "Dukan_x\\my-backend\\src\\services\\dashboard-analytics.service.ts", "source_location": "L141"}, {"id": "dashboard_analytics_service_dashboardanalyticsservice_getpaymentstatus", "label": ".getPaymentStatus()", "file_type": "code", "source_file": "Dukan_x\\my-backend\\src\\services\\dashboard-analytics.service.ts", "source_location": "L166"}, {"id": "dashboard_analytics_service_dashboardanalyticsservice_gettopproducts", "label": ".getTopProducts()", "file_type": "code", "source_file": "Dukan_x\\my-backend\\src\\services\\dashboard-analytics.service.ts", "source_location": "L190"}, {"id": "dashboard_analytics_service_dashboardanalyticsservice_getcategorysales", "label": ".getCategorySales()", "file_type": "code", "source_file": "Dukan_x\\my-backend\\src\\services\\dashboard-analytics.service.ts", "source_location": "L220"}, {"id": "dashboard_analytics_service_dashboardanalyticsservice_gethardwareprojectoutstanding", "label": ".getHardwareProjectOutstanding()", "file_type": "code", "source_file": "Dukan_x\\my-backend\\src\\services\\dashboard-analytics.service.ts", "source_location": "L243"}], "edges": [{"source": "dukan_x_my_backend_src_services_dashboard_analytics_service_ts", "target": "dukan_x_my_backend_src_config_dynamodb_config", "relation": "imports_from", "confidence": "EXTRACTED", "source_file": "Dukan_x\\my-backend\\src\\services\\dashboard-analytics.service.ts", "source_location": "L1", "weight": 1.0}, {"source": "dukan_x_my_backend_src_services_dashboard_analytics_service_ts", "target": "dashboard_analytics_service_todayrange", "relation": "contains", "confidence": "EXTRACTED", "source_file": "Dukan_x\\my-backend\\src\\services\\dashboard-analytics.service.ts", "source_location": "L12", "weight": 1.0}, {"source": "dukan_x_my_backend_src_services_dashboard_analytics_service_ts", "target": "dashboard_analytics_service_tomonthstart", "relation": "contains", "confidence": "EXTRACTED", "source_file": "Dukan_x\\my-backend\\src\\services\\dashboard-analytics.service.ts", "source_location": "L23", "weight": 1.0}, {"source": "dukan_x_my_backend_src_services_dashboard_analytics_service_ts", "target": "dashboard_analytics_service_tomonthkey", "relation": "contains", "confidence": "EXTRACTED", "source_file": "Dukan_x\\my-backend\\src\\services\\dashboard-analytics.service.ts", "source_location": "L27", "weight": 1.0}, {"source": "dukan_x_my_backend_src_services_dashboard_analytics_service_ts", "target": "dashboard_analytics_service_isactiveinvoice", "relation": "contains", "confidence": "EXTRACTED", "source_file": "Dukan_x\\my-backend\\src\\services\\dashboard-analytics.service.ts", "source_location": "L31", "weight": 1.0}, {"source": "dukan_x_my_backend_src_services_dashboard_analytics_service_ts", "target": "dashboard_analytics_service_toamount", "relation": "contains", "confidence": "EXTRACTED", "source_file": "Dukan_x\\my-backend\\src\\services\\dashboard-analytics.service.ts", "source_location": "L37", "weight": 1.0}, {"source": "dukan_x_my_backend_src_services_dashboard_analytics_service_ts", "target": "dashboard_analytics_service_fetchinvoicesinrange", "relation": "contains", "confidence": "EXTRACTED", "source_file": "Dukan_x\\my-backend\\src\\services\\dashboard-analytics.service.ts", "source_location": "L42", "weight": 1.0}, {"source": "dukan_x_my_backend_src_services_dashboard_analytics_service_ts", "target": "dashboard_analytics_service_fetchallactiveinvoices", "relation": "contains", "confidence": "EXTRACTED", "source_file": "Dukan_x\\my-backend\\src\\services\\dashboard-analytics.service.ts", "source_location": "L55", "weight": 1.0}, {"source": "dukan_x_my_backend_src_services_dashboard_analytics_service_ts", "target": "dashboard_analytics_service_dashboardanalyticsservice", "relation": "contains", "confidence": "EXTRACTED", "source_file": "Dukan_x\\my-backend\\src\\services\\dashboard-analytics.service.ts", "source_location": "L63", "weight": 1.0}, {"source": "dashboard_analytics_service_dashboardanalyticsservice", "target": "dashboard_analytics_service_dashboardanalyticsservice_getdashboardsummary", "relation": "method", "confidence": "EXTRACTED", "source_file": "Dukan_x\\my-backend\\src\\services\\dashboard-analytics.service.ts", "source_location": "L64", "weight": 1.0}, {"source": "dashboard_analytics_service_dashboardanalyticsservice", "target": "dashboard_analytics_service_dashboardanalyticsservice_getsalestrend", "relation": "method", "confidence": "EXTRACTED", "source_file": "Dukan_x\\my-backend\\src\\services\\dashboard-analytics.service.ts", "source_location": "L108", "weight": 1.0}, {"source": "dashboard_analytics_service_dashboardanalyticsservice", "target": "dashboard_analytics_service_dashboardanalyticsservice_getrevenuemonthly", "relation": "method", "confidence": "EXTRACTED", "source_file": "Dukan_x\\my-backend\\src\\services\\dashboard-analytics.service.ts", "source_location": "L141", "weight": 1.0}, {"source": "dashboard_analytics_service_dashboardanalyticsservice", "target": "dashboard_analytics_service_dashboardanalyticsservice_getpaymentstatus", "relation": "method", "confidence": "EXTRACTED", "source_file": "Dukan_x\\my-backend\\src\\services\\dashboard-analytics.service.ts", "source_location": "L166", "weight": 1.0}, {"source": "dashboard_analytics_service_dashboardanalyticsservice", "target": "dashboard_analytics_service_dashboardanalyticsservice_gettopproducts", "relation": "method", "confidence": "EXTRACTED", "source_file": "Dukan_x\\my-backend\\src\\services\\dashboard-analytics.service.ts", "source_location": "L190", "weight": 1.0}, {"source": "dashboard_analytics_service_dashboardanalyticsservice", "target": "dashboard_analytics_service_dashboardanalyticsservice_getcategorysales", "relation": "method", "confidence": "EXTRACTED", "source_file": "Dukan_x\\my-backend\\src\\services\\dashboard-analytics.service.ts", "source_location": "L220", "weight": 1.0}, {"source": "dashboard_analytics_service_dashboardanalyticsservice", "target": "dashboard_analytics_service_dashboardanalyticsservice_gethardwareprojectoutstanding", "relation": "method", "confidence": "EXTRACTED", "source_file": "Dukan_x\\my-backend\\src\\services\\dashboard-analytics.service.ts", "source_location": "L243", "weight": 1.0}, {"source": "dashboard_analytics_service_dashboardanalyticsservice_getdashboardsummary", "target": "dashboard_analytics_service_todayrange", "relation": "calls", "confidence": "EXTRACTED", "source_file": "Dukan_x\\my-backend\\src\\services\\dashboard-analytics.service.ts", "source_location": "L65", "weight": 1.0}, {"source": "dashboard_analytics_service_dashboardanalyticsservice_getdashboardsummary", "target": "dashboard_analytics_service_tomonthstart", "relation": "calls", "confidence": "EXTRACTED", "source_file": "Dukan_x\\my-backend\\src\\services\\dashboard-analytics.service.ts", "source_location": "L67", "weight": 1.0}, {"source": "dashboard_analytics_service_dashboardanalyticsservice_getdashboardsummary", "target": "dashboard_analytics_service_fetchinvoicesinrange", "relation": "calls", "confidence": "EXTRACTED", "source_file": "Dukan_x\\my-backend\\src\\services\\dashboard-analytics.service.ts", "source_location": "L71", "weight": 1.0}, {"source": "dashboard_analytics_service_dashboardanalyticsservice_getdashboardsummary", "target": "dashboard_analytics_service_fetchallactiveinvoices", "relation": "calls", "confidence": "EXTRACTED", "source_file": "Dukan_x\\my-backend\\src\\services\\dashboard-analytics.service.ts", "source_location": "L73", "weight": 1.0}, {"source": "dashboard_analytics_service_dashboardanalyticsservice_getsalestrend", "target": "dashboard_analytics_service_todayrange", "relation": "calls", "confidence": "EXTRACTED", "source_file": "Dukan_x\\my-backend\\src\\services\\dashboard-analytics.service.ts", "source_location": "L110", "weight": 1.0}, {"source": "dashboard_analytics_service_dashboardanalyticsservice_getsalestrend", "target": "dashboard_analytics_service_fetchinvoicesinrange", "relation": "calls", "confidence": "EXTRACTED", "source_file": "Dukan_x\\my-backend\\src\\services\\dashboard-analytics.service.ts", "source_location": "L111", "weight": 1.0}, {"source": "dashboard_analytics_service_dashboardanalyticsservice_getsalestrend", "target": "dashboard_analytics_service_toamount", "relation": "calls", "confidence": "EXTRACTED", "source_file": "Dukan_x\\my-backend\\src\\services\\dashboard-analytics.service.ts", "source_location": "L125", "weight": 1.0}, {"source": "dashboard_analytics_service_dashboardanalyticsservice_getrevenuemonthly", "target": "dashboard_analytics_service_fetchallactiveinvoices", "relation": "calls", "confidence": "EXTRACTED", "source_file": "Dukan_x\\my-backend\\src\\services\\dashboard-analytics.service.ts", "source_location": "L143", "weight": 1.0}, {"source": "dashboard_analytics_service_dashboardanalyticsservice_getrevenuemonthly", "target": "dashboard_analytics_service_tomonthkey", "relation": "calls", "confidence": "EXTRACTED", "source_file": "Dukan_x\\my-backend\\src\\services\\dashboard-analytics.service.ts", "source_location": "L149", "weight": 1.0}, {"source": "dashboard_analytics_service_dashboardanalyticsservice_getrevenuemonthly", "target": "dashboard_analytics_service_toamount", "relation": "calls", "confidence": "EXTRACTED", "source_file": "Dukan_x\\my-backend\\src\\services\\dashboard-analytics.service.ts", "source_location": "L156", "weight": 1.0}, {"source": "dashboard_analytics_service_dashboardanalyticsservice_getpaymentstatus", "target": "dashboard_analytics_service_fetchallactiveinvoices", "relation": "calls", "confidence": "EXTRACTED", "source_file": "Dukan_x\\my-backend\\src\\services\\dashboard-analytics.service.ts", "source_location": "L167", "weight": 1.0}, {"source": "dashboard_analytics_service_dashboardanalyticsservice_getpaymentstatus", "target": "dashboard_analytics_service_toamount", "relation": "calls", "confidence": "EXTRACTED", "source_file": "Dukan_x\\my-backend\\src\\services\\dashboard-analytics.service.ts", "source_location": "L173", "weight": 1.0}, {"source": "dashboard_analytics_service_dashboardanalyticsservice_gettopproducts", "target": "dashboard_analytics_service_todayrange", "relation": "calls", "confidence": "EXTRACTED", "source_file": "Dukan_x\\my-backend\\src\\services\\dashboard-analytics.service.ts", "source_location": "L193", "weight": 1.0}, {"source": "dashboard_analytics_service_dashboardanalyticsservice_gettopproducts", "target": "dashboard_analytics_service_fetchinvoicesinrange", "relation": "calls", "confidence": "EXTRACTED", "source_file": "Dukan_x\\my-backend\\src\\services\\dashboard-analytics.service.ts", "source_location": "L194", "weight": 1.0}, {"source": "dashboard_analytics_service_dashboardanalyticsservice_gettopproducts", "target": "dashboard_analytics_service_toamount", "relation": "calls", "confidence": "EXTRACTED", "source_file": "Dukan_x\\my-backend\\src\\services\\dashboard-analytics.service.ts", "source_location": "L204", "weight": 1.0}, {"source": "dashboard_analytics_service_dashboardanalyticsservice_getcategorysales", "target": "dashboard_analytics_service_todayrange", "relation": "calls", "confidence": "EXTRACTED", "source_file": "Dukan_x\\my-backend\\src\\services\\dashboard-analytics.service.ts", "source_location": "L222", "weight": 1.0}, {"source": "dashboard_analytics_service_dashboardanalyticsservice_getcategorysales", "target": "dashboard_analytics_service_fetchinvoicesinrange", "relation": "calls", "confidence": "EXTRACTED", "source_file": "Dukan_x\\my-backend\\src\\services\\dashboard-analytics.service.ts", "source_location": "L223", "weight": 1.0}, {"source": "dashboard_analytics_service_dashboardanalyticsservice_getcategorysales", "target": "dashboard_analytics_service_toamount", "relation": "calls", "confidence": "EXTRACTED", "source_file": "Dukan_x\\my-backend\\src\\services\\dashboard-analytics.service.ts", "source_location": "L233", "weight": 1.0}, {"source": "dashboard_analytics_service_dashboardanalyticsservice_gethardwareprojectoutstanding", "target": "dashboard_analytics_service_toamount", "relation": "calls", "confidence": "EXTRACTED", "source_file": "Dukan_x\\my-backend\\src\\services\\dashboard-analytics.service.ts", "source_location": "L270", "weight": 1.0}], "raw_calls": [{"caller_nid": "dashboard_analytics_service_todayrange", "callee": "setUTCDate", "source_file": "Dukan_x\\my-backend\\src\\services\\dashboard-analytics.service.ts", "source_location": "L15"}, {"caller_nid": "dashboard_analytics_service_todayrange", "callee": "getUTCDate", "source_file": "Dukan_x\\my-backend\\src\\services\\dashboard-analytics.service.ts", "source_location": "L15"}, {"caller_nid": "dashboard_analytics_service_todayrange", "callee": "setUTCHours", "source_file": "Dukan_x\\my-backend\\src\\services\\dashboard-analytics.service.ts", "source_location": "L16"}, {"caller_nid": "dashboard_analytics_service_todayrange", "callee": "setUTCDate", "source_file": "Dukan_x\\my-backend\\src\\services\\dashboard-analytics.service.ts", "source_location": "L18"}, {"caller_nid": "dashboard_analytics_service_todayrange", "callee": "getUTCDate", "source_file": "Dukan_x\\my-backend\\src\\services\\dashboard-analytics.service.ts", "source_location": "L18"}, {"caller_nid": "dashboard_analytics_service_todayrange", "callee": "setUTCHours", "source_file": "Dukan_x\\my-backend\\src\\services\\dashboard-analytics.service.ts", "source_location": "L19"}, {"caller_nid": "dashboard_analytics_service_todayrange", "callee": "toISOString", "source_file": "Dukan_x\\my-backend\\src\\services\\dashboard-analytics.service.ts", "source_location": "L20"}, {"caller_nid": "dashboard_analytics_service_todayrange", "callee": "toISOString", "source_file": "Dukan_x\\my-backend\\src\\services\\dashboard-analytics.service.ts", "source_location": "L20"}, {"caller_nid": "dashboard_analytics_service_tomonthstart", "callee": "UTC", "source_file": "Dukan_x\\my-backend\\src\\services\\dashboard-analytics.service.ts", "source_location": "L24"}, {"caller_nid": "dashboard_analytics_service_tomonthstart", "callee": "getUTCFullYear", "source_file": "Dukan_x\\my-backend\\src\\services\\dashboard-analytics.service.ts", "source_location": "L24"}, {"caller_nid": "dashboard_analytics_service_tomonthstart", "callee": "getUTCMonth", "source_file": "Dukan_x\\my-backend\\src\\services\\dashboard-analytics.service.ts", "source_location": "L24"}, {"caller_nid": "dashboard_analytics_service_tomonthkey", "callee": "getUTCFullYear", "source_file": "Dukan_x\\my-backend\\src\\services\\dashboard-analytics.service.ts", "source_location": "L28"}, {"caller_nid": "dashboard_analytics_service_tomonthkey", "callee": "padStart", "source_file": "Dukan_x\\my-backend\\src\\services\\dashboard-analytics.service.ts", "source_location": "L28"}, {"caller_nid": "dashboard_analytics_service_tomonthkey", "callee": "String", "source_file": "Dukan_x\\my-backend\\src\\services\\dashboard-analytics.service.ts", "source_location": "L28"}, {"caller_nid": "dashboard_analytics_service_tomonthkey", "callee": "getUTCMonth", "source_file": "Dukan_x\\my-backend\\src\\services\\dashboard-analytics.service.ts", "source_location": "L28"}, {"caller_nid": "dashboard_analytics_service_isactiveinvoice", "callee": "toLowerCase", "source_file": "Dukan_x\\my-backend\\src\\services\\dashboard-analytics.service.ts", "source_location": "L33"}, {"caller_nid": "dashboard_analytics_service_isactiveinvoice", "callee": "String", "source_file": "Dukan_x\\my-backend\\src\\services\\dashboard-analytics.service.ts", "source_location": "L33"}, {"caller_nid": "dashboard_analytics_service_toamount", "callee": "Number", "source_file": "Dukan_x\\my-backend\\src\\services\\dashboard-analytics.service.ts", "source_location": "L38"}, {"caller_nid": "dashboard_analytics_service_toamount", "callee": "isFinite", "source_file": "Dukan_x\\my-backend\\src\\services\\dashboard-analytics.service.ts", "source_location": "L39"}, {"caller_nid": "dashboard_analytics_service_fetchinvoicesinrange", "callee": "tenantPK", "source_file": "Dukan_x\\my-backend\\src\\services\\dashboard-analytics.service.ts", "source_location": "L43"}, {"caller_nid": "dashboard_analytics_service_fetchinvoicesinrange", "callee": "await queryAllItems", "source_file": "Dukan_x\\my-backend\\src\\services\\dashboard-analytics.service.ts", "source_location": "L44"}, {"caller_nid": "dashboard_analytics_service_fetchinvoicesinrange", "callee": "filter", "source_file": "Dukan_x\\my-backend\\src\\services\\dashboard-analytics.service.ts", "source_location": "L52"}, {"caller_nid": "dashboard_analytics_service_fetchallactiveinvoices", "callee": "tenantPK", "source_file": "Dukan_x\\my-backend\\src\\services\\dashboard-analytics.service.ts", "source_location": "L56"}, {"caller_nid": "dashboard_analytics_service_fetchallactiveinvoices", "callee": "await queryAllItems", "source_file": "Dukan_x\\my-backend\\src\\services\\dashboard-analytics.service.ts", "source_location": "L57"}, {"caller_nid": "dashboard_analytics_service_fetchallactiveinvoices", "callee": "filter", "source_file": "Dukan_x\\my-backend\\src\\services\\dashboard-analytics.service.ts", "source_location": "L60"}, {"caller_nid": "dashboard_analytics_service_dashboardanalyticsservice_getdashboardsummary", "callee": "toISOString", "source_file": "Dukan_x\\my-backend\\src\\services\\dashboard-analytics.service.ts", "source_location": "L67"}, {"caller_nid": "dashboard_analytics_service_dashboardanalyticsservice_getdashboardsummary", "callee": "toISOString", "source_file": "Dukan_x\\my-backend\\src\\services\\dashboard-analytics.service.ts", "source_location": "L68"}, {"caller_nid": "dashboard_analytics_service_dashboardanalyticsservice_getdashboardsummary", "callee": "setUTCMonth", "source_file": "Dukan_x\\my-backend\\src\\services\\dashboard-analytics.service.ts", "source_location": "L68"}, {"caller_nid": "dashboard_analytics_service_dashboardanalyticsservice_getdashboardsummary", "callee": "getUTCMonth", "source_file": "Dukan_x\\my-backend\\src\\services\\dashboard-analytics.service.ts", "source_location": "L68"}, {"caller_nid": "dashboard_analytics_service_dashboardanalyticsservice_getdashboardsummary", "callee": "all", "source_file": "Dukan_x\\my-backend\\src\\services\\dashboard-analytics.service.ts", "source_location": "L70"}, {"caller_nid": "dashboard_analytics_service_dashboardanalyticsservice_getdashboardsummary", "callee": "queryAllItems", "source_file": "Dukan_x\\my-backend\\src\\services\\dashboard-analytics.service.ts", "source_location": "L74"}, {"caller_nid": "dashboard_analytics_service_dashboardanalyticsservice_getdashboardsummary", "callee": "tenantPK", "source_file": "Dukan_x\\my-backend\\src\\services\\dashboard-analytics.service.ts", "source_location": "L74"}, {"caller_nid": "dashboard_analytics_service_dashboardanalyticsservice_getdashboardsummary", "callee": "catch", "source_file": "Dukan_x\\my-backend\\src\\services\\dashboard-analytics.service.ts", "source_location": "L75"}, {"caller_nid": "dashboard_analytics_service_dashboardanalyticsservice_getdashboardsummary", "callee": "then", "source_file": "Dukan_x\\my-backend\\src\\services\\dashboard-analytics.service.ts", "source_location": "L75"}, {"caller_nid": "dashboard_analytics_service_dashboardanalyticsservice_getdashboardsummary", "callee": "queryItems", "source_file": "Dukan_x\\my-backend\\src\\services\\dashboard-analytics.service.ts", "source_location": "L75"}, {"caller_nid": "dashboard_analytics_service_dashboardanalyticsservice_getdashboardsummary", "callee": "tenantPK", "source_file": "Dukan_x\\my-backend\\src\\services\\dashboard-analytics.service.ts", "source_location": "L75"}, {"caller_nid": "dashboard_analytics_service_dashboardanalyticsservice_getdashboardsummary", "callee": "reduce", "source_file": "Dukan_x\\my-backend\\src\\services\\dashboard-analytics.service.ts", "source_location": "L82"}, {"caller_nid": "dashboard_analytics_service_dashboardanalyticsservice_getdashboardsummary", "callee": "reduce", "source_file": "Dukan_x\\my-backend\\src\\services\\dashboard-analytics.service.ts", "source_location": "L83"}, {"caller_nid": "dashboard_analytics_service_dashboardanalyticsservice_getdashboardsummary", "callee": "reduce", "source_file": "Dukan_x\\my-backend\\src\\services\\dashboard-analytics.service.ts", "source_location": "L84"}, {"caller_nid": "dashboard_analytics_service_dashboardanalyticsservice_getdashboardsummary", "callee": "reduce", "source_file": "Dukan_x\\my-backend\\src\\services\\dashboard-analytics.service.ts", "source_location": "L85"}, {"caller_nid": "dashboard_analytics_service_dashboardanalyticsservice_getdashboardsummary", "callee": "filter", "source_file": "Dukan_x\\my-backend\\src\\services\\dashboard-analytics.service.ts", "source_location": "L87"}, {"caller_nid": "dashboard_analytics_service_dashboardanalyticsservice_getdashboardsummary", "callee": "map", "source_file": "Dukan_x\\my-backend\\src\\services\\dashboard-analytics.service.ts", "source_location": "L96"}, {"caller_nid": "dashboard_analytics_service_dashboardanalyticsservice_getdashboardsummary", "callee": "filter", "source_file": "Dukan_x\\my-backend\\src\\services\\dashboard-analytics.service.ts", "source_location": "L96"}, {"caller_nid": "dashboard_analytics_service_dashboardanalyticsservice_getdashboardsummary", "callee": "toISOString", "source_file": "Dukan_x\\my-backend\\src\\services\\dashboard-analytics.service.ts", "source_location": "L104"}, {"caller_nid": "dashboard_analytics_service_dashboardanalyticsservice_getsalestrend", "callee": "setUTCDate", "source_file": "Dukan_x\\my-backend\\src\\services\\dashboard-analytics.service.ts", "source_location": "L116"}, {"caller_nid": "dashboard_analytics_service_dashboardanalyticsservice_getsalestrend", "callee": "getUTCDate", "source_file": "Dukan_x\\my-backend\\src\\services\\dashboard-analytics.service.ts", "source_location": "L116"}, {"caller_nid": "dashboard_analytics_service_dashboardanalyticsservice_getsalestrend", "callee": "slice", "source_file": "Dukan_x\\my-backend\\src\\services\\dashboard-analytics.service.ts", "source_location": "L117"}, {"caller_nid": "dashboard_analytics_service_dashboardanalyticsservice_getsalestrend", "callee": "toISOString", "source_file": "Dukan_x\\my-backend\\src\\services\\dashboard-analytics.service.ts", "source_location": "L117"}, {"caller_nid": "dashboard_analytics_service_dashboardanalyticsservice_getsalestrend", "callee": "set", "source_file": "Dukan_x\\my-backend\\src\\services\\dashboard-analytics.service.ts", "source_location": "L118"}, {"caller_nid": "dashboard_analytics_service_dashboardanalyticsservice_getsalestrend", "callee": "slice", "source_file": "Dukan_x\\my-backend\\src\\services\\dashboard-analytics.service.ts", "source_location": "L122"}, {"caller_nid": "dashboard_analytics_service_dashboardanalyticsservice_getsalestrend", "callee": "String", "source_file": "Dukan_x\\my-backend\\src\\services\\dashboard-analytics.service.ts", "source_location": "L122"}, {"caller_nid": "dashboard_analytics_service_dashboardanalyticsservice_getsalestrend", "callee": "has", "source_file": "Dukan_x\\my-backend\\src\\services\\dashboard-analytics.service.ts", "source_location": "L123"}, {"caller_nid": "dashboard_analytics_service_dashboardanalyticsservice_getsalestrend", "callee": "get", "source_file": "Dukan_x\\my-backend\\src\\services\\dashboard-analytics.service.ts", "source_location": "L124"}, {"caller_nid": "dashboard_analytics_service_dashboardanalyticsservice_getsalestrend", "callee": "set", "source_file": "Dukan_x\\my-backend\\src\\services\\dashboard-analytics.service.ts", "source_location": "L127"}, {"caller_nid": "dashboard_analytics_service_dashboardanalyticsservice_getsalestrend", "callee": "map", "source_file": "Dukan_x\\my-backend\\src\\services\\dashboard-analytics.service.ts", "source_location": "L132"}, {"caller_nid": "dashboard_analytics_service_dashboardanalyticsservice_getsalestrend", "callee": "from", "source_file": "Dukan_x\\my-backend\\src\\services\\dashboard-analytics.service.ts", "source_location": "L132"}, {"caller_nid": "dashboard_analytics_service_dashboardanalyticsservice_getsalestrend", "callee": "entries", "source_file": "Dukan_x\\my-backend\\src\\services\\dashboard-analytics.service.ts", "source_location": "L132"}, {"caller_nid": "dashboard_analytics_service_dashboardanalyticsservice_getsalestrend", "callee": "toISOString", "source_file": "Dukan_x\\my-backend\\src\\services\\dashboard-analytics.service.ts", "source_location": "L137"}, {"caller_nid": "dashboard_analytics_service_dashboardanalyticsservice_getrevenuemonthly", "callee": "min", "source_file": "Dukan_x\\my-backend\\src\\services\\dashboard-analytics.service.ts", "source_location": "L142"}, {"caller_nid": "dashboard_analytics_service_dashboardanalyticsservice_getrevenuemonthly", "callee": "max", "source_file": "Dukan_x\\my-backend\\src\\services\\dashboard-analytics.service.ts", "source_location": "L142"}, {"caller_nid": "dashboard_analytics_service_dashboardanalyticsservice_getrevenuemonthly", "callee": "UTC", "source_file": "Dukan_x\\my-backend\\src\\services\\dashboard-analytics.service.ts", "source_location": "L148"}, {"caller_nid": "dashboard_analytics_service_dashboardanalyticsservice_getrevenuemonthly", "callee": "getUTCFullYear", "source_file": "Dukan_x\\my-backend\\src\\services\\dashboard-analytics.service.ts", "source_location": "L148"}, {"caller_nid": "dashboard_analytics_service_dashboardanalyticsservice_getrevenuemonthly", "callee": "getUTCMonth", "source_file": "Dukan_x\\my-backend\\src\\services\\dashboard-analytics.service.ts", "source_location": "L148"}, {"caller_nid": "dashboard_analytics_service_dashboardanalyticsservice_getrevenuemonthly", "callee": "set", "source_file": "Dukan_x\\my-backend\\src\\services\\dashboard-analytics.service.ts", "source_location": "L149"}, {"caller_nid": "dashboard_analytics_service_dashboardanalyticsservice_getrevenuemonthly", "callee": "has", "source_file": "Dukan_x\\my-backend\\src\\services\\dashboard-analytics.service.ts", "source_location": "L155"}, {"caller_nid": "dashboard_analytics_service_dashboardanalyticsservice_getrevenuemonthly", "callee": "set", "source_file": "Dukan_x\\my-backend\\src\\services\\dashboard-analytics.service.ts", "source_location": "L156"}, {"caller_nid": "dashboard_analytics_service_dashboardanalyticsservice_getrevenuemonthly", "callee": "get", "source_file": "Dukan_x\\my-backend\\src\\services\\dashboard-analytics.service.ts", "source_location": "L156"}, {"caller_nid": "dashboard_analytics_service_dashboardanalyticsservice_getrevenuemonthly", "callee": "map", "source_file": "Dukan_x\\my-backend\\src\\services\\dashboard-analytics.service.ts", "source_location": "L159"}, {"caller_nid": "dashboard_analytics_service_dashboardanalyticsservice_getrevenuemonthly", "callee": "from", "source_file": "Dukan_x\\my-backend\\src\\services\\dashboard-analytics.service.ts", "source_location": "L159"}, {"caller_nid": "dashboard_analytics_service_dashboardanalyticsservice_getrevenuemonthly", "callee": "entries", "source_file": "Dukan_x\\my-backend\\src\\services\\dashboard-analytics.service.ts", "source_location": "L159"}, {"caller_nid": "dashboard_analytics_service_dashboardanalyticsservice_getrevenuemonthly", "callee": "toISOString", "source_file": "Dukan_x\\my-backend\\src\\services\\dashboard-analytics.service.ts", "source_location": "L163"}, {"caller_nid": "dashboard_analytics_service_dashboardanalyticsservice_getpaymentstatus", "callee": "toISOString", "source_file": "Dukan_x\\my-backend\\src\\services\\dashboard-analytics.service.ts", "source_location": "L186"}, {"caller_nid": "dashboard_analytics_service_dashboardanalyticsservice_gettopproducts", "callee": "min", "source_file": "Dukan_x\\my-backend\\src\\services\\dashboard-analytics.service.ts", "source_location": "L191"}, {"caller_nid": "dashboard_analytics_service_dashboardanalyticsservice_gettopproducts", "callee": "max", "source_file": "Dukan_x\\my-backend\\src\\services\\dashboard-analytics.service.ts", "source_location": "L191"}, {"caller_nid": "dashboard_analytics_service_dashboardanalyticsservice_gettopproducts", "callee": "min", "source_file": "Dukan_x\\my-backend\\src\\services\\dashboard-analytics.service.ts", "source_location": "L192"}, {"caller_nid": "dashboard_analytics_service_dashboardanalyticsservice_gettopproducts", "callee": "max", "source_file": "Dukan_x\\my-backend\\src\\services\\dashboard-analytics.service.ts", "source_location": "L192"}, {"caller_nid": "dashboard_analytics_service_dashboardanalyticsservice_gettopproducts", "callee": "await queryAllItems", "source_file": "Dukan_x\\my-backend\\src\\services\\dashboard-analytics.service.ts", "source_location": "L200"}, {"caller_nid": "dashboard_analytics_service_dashboardanalyticsservice_gettopproducts", "callee": "invoiceLineItemPK", "source_file": "Dukan_x\\my-backend\\src\\services\\dashboard-analytics.service.ts", "source_location": "L200"}, {"caller_nid": "dashboard_analytics_service_dashboardanalyticsservice_gettopproducts", "callee": "get", "source_file": "Dukan_x\\my-backend\\src\\services\\dashboard-analytics.service.ts", "source_location": "L206"}, {"caller_nid": "dashboard_analytics_service_dashboardanalyticsservice_gettopproducts", "callee": "set", "source_file": "Dukan_x\\my-backend\\src\\services\\dashboard-analytics.service.ts", "source_location": "L209"}, {"caller_nid": "dashboard_analytics_service_dashboardanalyticsservice_gettopproducts", "callee": "slice", "source_file": "Dukan_x\\my-backend\\src\\services\\dashboard-analytics.service.ts", "source_location": "L213"}, {"caller_nid": "dashboard_analytics_service_dashboardanalyticsservice_gettopproducts", "callee": "sort", "source_file": "Dukan_x\\my-backend\\src\\services\\dashboard-analytics.service.ts", "source_location": "L213"}, {"caller_nid": "dashboard_analytics_service_dashboardanalyticsservice_gettopproducts", "callee": "from", "source_file": "Dukan_x\\my-backend\\src\\services\\dashboard-analytics.service.ts", "source_location": "L213"}, {"caller_nid": "dashboard_analytics_service_dashboardanalyticsservice_gettopproducts", "callee": "values", "source_file": "Dukan_x\\my-backend\\src\\services\\dashboard-analytics.service.ts", "source_location": "L213"}, {"caller_nid": "dashboard_analytics_service_dashboardanalyticsservice_gettopproducts", "callee": "toISOString", "source_file": "Dukan_x\\my-backend\\src\\services\\dashboard-analytics.service.ts", "source_location": "L217"}, {"caller_nid": "dashboard_analytics_service_dashboardanalyticsservice_getcategorysales", "callee": "min", "source_file": "Dukan_x\\my-backend\\src\\services\\dashboard-analytics.service.ts", "source_location": "L221"}, {"caller_nid": "dashboard_analytics_service_dashboardanalyticsservice_getcategorysales", "callee": "max", "source_file": "Dukan_x\\my-backend\\src\\services\\dashboard-analytics.service.ts", "source_location": "L221"}, {"caller_nid": "dashboard_analytics_service_dashboardanalyticsservice_getcategorysales", "callee": "await queryAllItems", "source_file": "Dukan_x\\my-backend\\src\\services\\dashboard-analytics.service.ts", "source_location": "L229"}, {"caller_nid": "dashboard_analytics_service_dashboardanalyticsservice_getcategorysales", "callee": "invoiceLineItemPK", "source_file": "Dukan_x\\my-backend\\src\\services\\dashboard-analytics.service.ts", "source_location": "L229"}, {"caller_nid": "dashboard_analytics_service_dashboardanalyticsservice_getcategorysales", "callee": "String", "source_file": "Dukan_x\\my-backend\\src\\services\\dashboard-analytics.service.ts", "source_location": "L231"}, {"caller_nid": "dashboard_analytics_service_dashboardanalyticsservice_getcategorysales", "callee": "get", "source_file": "Dukan_x\\my-backend\\src\\services\\dashboard-analytics.service.ts", "source_location": "L232"}, {"caller_nid": "dashboard_analytics_service_dashboardanalyticsservice_getcategorysales", "callee": "set", "source_file": "Dukan_x\\my-backend\\src\\services\\dashboard-analytics.service.ts", "source_location": "L235"}, {"caller_nid": "dashboard_analytics_service_dashboardanalyticsservice_getcategorysales", "callee": "sort", "source_file": "Dukan_x\\my-backend\\src\\services\\dashboard-analytics.service.ts", "source_location": "L239"}, {"caller_nid": "dashboard_analytics_service_dashboardanalyticsservice_getcategorysales", "callee": "from", "source_file": "Dukan_x\\my-backend\\src\\services\\dashboard-analytics.service.ts", "source_location": "L239"}, {"caller_nid": "dashboard_analytics_service_dashboardanalyticsservice_getcategorysales", "callee": "values", "source_file": "Dukan_x\\my-backend\\src\\services\\dashboard-analytics.service.ts", "source_location": "L239"}, {"caller_nid": "dashboard_analytics_service_dashboardanalyticsservice_getcategorysales", "callee": "toISOString", "source_file": "Dukan_x\\my-backend\\src\\services\\dashboard-analytics.service.ts", "source_location": "L240"}, {"caller_nid": "dashboard_analytics_service_dashboardanalyticsservice_gethardwareprojectoutstanding", "callee": "min", "source_file": "Dukan_x\\my-backend\\src\\services\\dashboard-analytics.service.ts", "source_location": "L244"}, {"caller_nid": "dashboard_analytics_service_dashboardanalyticsservice_gethardwareprojectoutstanding", "callee": "max", "source_file": "Dukan_x\\my-backend\\src\\services\\dashboard-analytics.service.ts", "source_location": "L244"}, {"caller_nid": "dashboard_analytics_service_dashboardanalyticsservice_gethardwareprojectoutstanding", "callee": "all", "source_file": "Dukan_x\\my-backend\\src\\services\\dashboard-analytics.service.ts", "source_location": "L245"}, {"caller_nid": "dashboard_analytics_service_dashboardanalyticsservice_gethardwareprojectoutstanding", "callee": "queryAllItems", "source_file": "Dukan_x\\my-backend\\src\\services\\dashboard-analytics.service.ts", "source_location": "L246"}, {"caller_nid": "dashboard_analytics_service_dashboardanalyticsservice_gethardwareprojectoutstanding", "callee": "tenantPK", "source_file": "Dukan_x\\my-backend\\src\\services\\dashboard-analytics.service.ts", "source_location": "L246"}, {"caller_nid": "dashboard_analytics_service_dashboardanalyticsservice_gethardwareprojectoutstanding", "callee": "queryAllItems", "source_file": "Dukan_x\\my-backend\\src\\services\\dashboard-analytics.service.ts", "source_location": "L247"}, {"caller_nid": "dashboard_analytics_service_dashboardanalyticsservice_gethardwareprojectoutstanding", "callee": "tenantPK", "source_file": "Dukan_x\\my-backend\\src\\services\\dashboard-analytics.service.ts", "source_location": "L247"}, {"caller_nid": "dashboard_analytics_service_dashboardanalyticsservice_gethardwareprojectoutstanding", "callee": "queryAllItems", "source_file": "Dukan_x\\my-backend\\src\\services\\dashboard-analytics.service.ts", "source_location": "L248"}, {"caller_nid": "dashboard_analytics_service_dashboardanalyticsservice_gethardwareprojectoutstanding", "callee": "tenantPK", "source_file": "Dukan_x\\my-backend\\src\\services\\dashboard-analytics.service.ts", "source_location": "L248"}, {"caller_nid": "dashboard_analytics_service_dashboardanalyticsservice_gethardwareprojectoutstanding", "callee": "queryAllItems", "source_file": "Dukan_x\\my-backend\\src\\services\\dashboard-analytics.service.ts", "source_location": "L249"}, {"caller_nid": "dashboard_analytics_service_dashboardanalyticsservice_gethardwareprojectoutstanding", "callee": "tenantPK", "source_file": "Dukan_x\\my-backend\\src\\services\\dashboard-analytics.service.ts", "source_location": "L249"}, {"caller_nid": "dashboard_analytics_service_dashboardanalyticsservice_gethardwareprojectoutstanding", "callee": "filter", "source_file": "Dukan_x\\my-backend\\src\\services\\dashboard-analytics.service.ts", "source_location": "L252"}, {"caller_nid": "dashboard_analytics_service_dashboardanalyticsservice_gethardwareprojectoutstanding", "callee": "filter", "source_file": "Dukan_x\\my-backend\\src\\services\\dashboard-analytics.service.ts", "source_location": "L253"}, {"caller_nid": "dashboard_analytics_service_dashboardanalyticsservice_gethardwareprojectoutstanding", "callee": "filter", "source_file": "Dukan_x\\my-backend\\src\\services\\dashboard-analytics.service.ts", "source_location": "L254"}, {"caller_nid": "dashboard_analytics_service_dashboardanalyticsservice_gethardwareprojectoutstanding", "callee": "filter", "source_file": "Dukan_x\\my-backend\\src\\services\\dashboard-analytics.service.ts", "source_location": "L255"}, {"caller_nid": "dashboard_analytics_service_dashboardanalyticsservice_gethardwareprojectoutstanding", "callee": "toLowerCase", "source_file": "Dukan_x\\my-backend\\src\\services\\dashboard-analytics.service.ts", "source_location": "L259"}, {"caller_nid": "dashboard_analytics_service_dashboardanalyticsservice_gethardwareprojectoutstanding", "callee": "String", "source_file": "Dukan_x\\my-backend\\src\\services\\dashboard-analytics.service.ts", "source_location": "L259"}, {"caller_nid": "dashboard_analytics_service_dashboardanalyticsservice_gethardwareprojectoutstanding", "callee": "String", "source_file": "Dukan_x\\my-backend\\src\\services\\dashboard-analytics.service.ts", "source_location": "L260"}, {"caller_nid": "dashboard_analytics_service_dashboardanalyticsservice_gethardwareprojectoutstanding", "callee": "set", "source_file": "Dukan_x\\my-backend\\src\\services\\dashboard-analytics.service.ts", "source_location": "L262"}, {"caller_nid": "dashboard_analytics_service_dashboardanalyticsservice_gethardwareprojectoutstanding", "callee": "get", "source_file": "Dukan_x\\my-backend\\src\\services\\dashboard-analytics.service.ts", "source_location": "L262"}, {"caller_nid": "dashboard_analytics_service_dashboardanalyticsservice_gethardwareprojectoutstanding", "callee": "toLowerCase", "source_file": "Dukan_x\\my-backend\\src\\services\\dashboard-analytics.service.ts", "source_location": "L267"}, {"caller_nid": "dashboard_analytics_service_dashboardanalyticsservice_gethardwareprojectoutstanding", "callee": "String", "source_file": "Dukan_x\\my-backend\\src\\services\\dashboard-analytics.service.ts", "source_location": "L267"}, {"caller_nid": "dashboard_analytics_service_dashboardanalyticsservice_gethardwareprojectoutstanding", "callee": "String", "source_file": "Dukan_x\\my-backend\\src\\services\\dashboard-analytics.service.ts", "source_location": "L268"}, {"caller_nid": "dashboard_analytics_service_dashboardanalyticsservice_gethardwareprojectoutstanding", "callee": "set", "source_file": "Dukan_x\\my-backend\\src\\services\\dashboard-analytics.service.ts", "source_location": "L270"}, {"caller_nid": "dashboard_analytics_service_dashboardanalyticsservice_gethardwareprojectoutstanding", "callee": "get", "source_file": "Dukan_x\\my-backend\\src\\services\\dashboard-analytics.service.ts", "source_location": "L270"}, {"caller_nid": "dashboard_analytics_service_dashboardanalyticsservice_gethardwareprojectoutstanding", "callee": "map", "source_file": "Dukan_x\\my-backend\\src\\services\\dashboard-analytics.service.ts", "source_location": "L273"}, {"caller_nid": "dashboard_analytics_service_dashboardanalyticsservice_gethardwareprojectoutstanding", "callee": "slice", "source_file": "Dukan_x\\my-backend\\src\\services\\dashboard-analytics.service.ts", "source_location": "L286"}, {"caller_nid": "dashboard_analytics_service_dashboardanalyticsservice_gethardwareprojectoutstanding", "callee": "sort", "source_file": "Dukan_x\\my-backend\\src\\services\\dashboard-analytics.service.ts", "source_location": "L286"}, {"caller_nid": "dashboard_analytics_service_dashboardanalyticsservice_gethardwareprojectoutstanding", "callee": "filter", "source_file": "Dukan_x\\my-backend\\src\\services\\dashboard-analytics.service.ts", "source_location": "L290"}, {"caller_nid": "dashboard_analytics_service_dashboardanalyticsservice_gethardwareprojectoutstanding", "callee": "filter", "source_file": "Dukan_x\\my-backend\\src\\services\\dashboard-analytics.service.ts", "source_location": "L291"}, {"caller_nid": "dashboard_analytics_service_dashboardanalyticsservice_gethardwareprojectoutstanding", "callee": "toISOString", "source_file": "Dukan_x\\my-backend\\src\\services\\dashboard-analytics.service.ts", "source_location": "L298"}]}