{"nodes": [{"id": "dukan_x_lib_screens_dukanx_splash_screen_dart", "label": "dukanx_splash_screen.dart", "file_type": "code", "source_file": "Dukan_x\\lib\\screens\\dukanx_splash_screen.dart", "source_location": null}, {"id": "dukan_x_lib_screens_dukanx_splash_screen_dart_dukanxsplashscreen", "label": "DukanXSplashScreen", "file_type": "code", "source_file": "Dukan_x\\lib\\screens\\dukanx_splash_screen.dart", "source_location": null}, {"id": "dukan_x_lib_screens_dukanx_splash_screen_dart_dukanxsplashscreenstate", "label": "_DukanXSplashScreenState", "file_type": "code", "source_file": "Dukan_x\\lib\\screens\\dukanx_splash_screen.dart", "source_location": null}, {"id": "dukan_x_lib_screens_dukanx_splash_screen_dart_glowinglogo", "label": "_GlowingLogo", "file_type": "code", "source_file": "Dukan_x\\lib\\screens\\dukanx_splash_screen.dart", "source_location": null}, {"id": "dukan_x_lib_screens_dukanx_splash_screen_dart_glowringpainter", "label": "_GlowRingPainter", "file_type": "code", "source_file": "Dukan_x\\lib\\screens\\dukanx_splash_screen.dart", "source_location": null}, {"id": "dukan_x_lib_screens_dukanx_splash_screen_dart_spacebackground", "label": "_SpaceBackground", "file_type": "code", "source_file": "Dukan_x\\lib\\screens\\dukanx_splash_screen.dart", "source_location": null}, {"id": "dukan_x_lib_screens_dukanx_splash_screen_dart_bottomglow", "label": "_BottomGlow", "file_type": "code", "source_file": "Dukan_x\\lib\\screens\\dukanx_splash_screen.dart", "source_location": null}, {"id": "dukan_x_lib_screens_dukanx_splash_screen_dart_initstate", "label": "initState", "file_type": "code", "source_file": "Dukan_x\\lib\\screens\\dukanx_splash_screen.dart", "source_location": null}, {"id": "dukan_x_lib_screens_dukanx_splash_screen_dart_dispose", "label": "dispose", "file_type": "code", "source_file": "Dukan_x\\lib\\screens\\dukanx_splash_screen.dart", "source_location": null}, {"id": "dukan_x_lib_screens_dukanx_splash_screen_dart_build", "label": "build", "file_type": "code", "source_file": "Dukan_x\\lib\\screens\\dukanx_splash_screen.dart", "source_location": null}, {"id": "dukan_x_lib_screens_dukanx_splash_screen_dart_scaffold", "label": "Scaffold", "file_type": "code", "source_file": "Dukan_x\\lib\\screens\\dukanx_splash_screen.dart", "source_location": null}, {"id": "dukan_x_lib_screens_dukanx_splash_screen_dart_spacer", "label": "Spacer", "file_type": "code", "source_file": "Dukan_x\\lib\\screens\\dukanx_splash_screen.dart", "source_location": null}, {"id": "dukan_x_lib_screens_dukanx_splash_screen_dart_sizedbox", "label": "SizedBox", "file_type": "code", "source_file": "Dukan_x\\lib\\screens\\dukanx_splash_screen.dart", "source_location": null}, {"id": "dukan_x_lib_screens_dukanx_splash_screen_dart_color", "label": "Color", "file_type": "code", "source_file": "Dukan_x\\lib\\screens\\dukanx_splash_screen.dart", "source_location": null}, {"id": "dukan_x_lib_screens_dukanx_splash_screen_dart_animatedbuilder", "label": "AnimatedBuilder", "file_type": "code", "source_file": "Dukan_x\\lib\\screens\\dukanx_splash_screen.dart", "source_location": null}, {"id": "dukan_x_lib_screens_dukanx_splash_screen_dart_container", "label": "Container", "file_type": "code", "source_file": "Dukan_x\\lib\\screens\\dukanx_splash_screen.dart", "source_location": null}, {"id": "dukan_x_lib_screens_dukanx_splash_screen_dart_paint", "label": "paint", "file_type": "code", "source_file": "Dukan_x\\lib\\screens\\dukanx_splash_screen.dart", "source_location": null}, {"id": "dukan_x_lib_screens_dukanx_splash_screen_dart_shouldrepaint", "label": "shouldRepaint", "file_type": "code", "source_file": "Dukan_x\\lib\\screens\\dukanx_splash_screen.dart", "source_location": null}, {"id": "dukan_x_lib_screens_dukanx_splash_screen_dart_positioned", "label": "Positioned", "file_type": "code", "source_file": "Dukan_x\\lib\\screens\\dukanx_splash_screen.dart", "source_location": null}, {"id": "dart_math", "label": "dart:math", "file_type": "code", "source_file": "Dukan_x\\lib\\screens\\dukanx_splash_screen.dart", "source_location": null}, {"id": "package_flutter_material_dart", "label": "package:flutter/material.dart", "file_type": "code", "source_file": "Dukan_x\\lib\\screens\\dukanx_splash_screen.dart", "source_location": null}, {"id": "widgets_modern_ui_components_dart", "label": "../../widgets/modern_ui_components.dart", "file_type": "code", "source_file": "Dukan_x\\lib\\screens\\dukanx_splash_screen.dart", "source_location": null}, {"id": "core_startup_startup_manager_dart", "label": "../../core/startup/startup_manager.dart", "file_type": "code", "source_file": "Dukan_x\\lib\\screens\\dukanx_splash_screen.dart", "source_location": null}], "edges": [{"source": "dukan_x_lib_screens_dukanx_splash_screen_dart", "target": "dukan_x_lib_screens_dukanx_splash_screen_dart_dukanxsplashscreen", "relation": "defines", "confidence": "EXTRACTED", "confidence_score": 1.0, "source_file": "Dukan_x\\lib\\screens\\dukanx_splash_screen.dart", "source_location": null, "weight": 1.0}, {"source": "dukan_x_lib_screens_dukanx_splash_screen_dart", "target": "dukan_x_lib_screens_dukanx_splash_screen_dart_dukanxsplashscreenstate", "relation": "defines", "confidence": "EXTRACTED", "confidence_score": 1.0, "source_file": "Dukan_x\\lib\\screens\\dukanx_splash_screen.dart", "source_location": null, "weight": 1.0}, {"source": "dukan_x_lib_screens_dukanx_splash_screen_dart", "target": "dukan_x_lib_screens_dukanx_splash_screen_dart_glowinglogo", "relation": "defines", "confidence": "EXTRACTED", "confidence_score": 1.0, "source_file": "Dukan_x\\lib\\screens\\dukanx_splash_screen.dart", "source_location": null, "weight": 1.0}, {"source": "dukan_x_lib_screens_dukanx_splash_screen_dart", "target": "dukan_x_lib_screens_dukanx_splash_screen_dart_glowringpainter", "relation": "defines", "confidence": "EXTRACTED", "confidence_score": 1.0, "source_file": "Dukan_x\\lib\\screens\\dukanx_splash_screen.dart", "source_location": null, "weight": 1.0}, {"source": "dukan_x_lib_screens_dukanx_splash_screen_dart", "target": "dukan_x_lib_screens_dukanx_splash_screen_dart_spacebackground", "relation": "defines", "confidence": "EXTRACTED", "confidence_score": 1.0, "source_file": "Dukan_x\\lib\\screens\\dukanx_splash_screen.dart", "source_location": null, "weight": 1.0}, {"source": "dukan_x_lib_screens_dukanx_splash_screen_dart", "target": "dukan_x_lib_screens_dukanx_splash_screen_dart_bottomglow", "relation": "defines", "confidence": "EXTRACTED", "confidence_score": 1.0, "source_file": "Dukan_x\\lib\\screens\\dukanx_splash_screen.dart", "source_location": null, "weight": 1.0}, {"source": "dukan_x_lib_screens_dukanx_splash_screen_dart", "target": "dukan_x_lib_screens_dukanx_splash_screen_dart_initstate", "relation": "defines", "confidence": "EXTRACTED", "confidence_score": 1.0, "source_file": "Dukan_x\\lib\\screens\\dukanx_splash_screen.dart", "source_location": null, "weight": 1.0}, {"source": "dukan_x_lib_screens_dukanx_splash_screen_dart", "target": "dukan_x_lib_screens_dukanx_splash_screen_dart_dispose", "relation": "defines", "confidence": "EXTRACTED", "confidence_score": 1.0, "source_file": "Dukan_x\\lib\\screens\\dukanx_splash_screen.dart", "source_location": null, "weight": 1.0}, {"source": "dukan_x_lib_screens_dukanx_splash_screen_dart", "target": "dukan_x_lib_screens_dukanx_splash_screen_dart_build", "relation": "defines", "confidence": "EXTRACTED", "confidence_score": 1.0, "source_file": "Dukan_x\\lib\\screens\\dukanx_splash_screen.dart", "source_location": null, "weight": 1.0}, {"source": "dukan_x_lib_screens_dukanx_splash_screen_dart", "target": "dukan_x_lib_screens_dukanx_splash_screen_dart_scaffold", "relation": "defines", "confidence": "EXTRACTED", "confidence_score": 1.0, "source_file": "Dukan_x\\lib\\screens\\dukanx_splash_screen.dart", "source_location": null, "weight": 1.0}, {"source": "dukan_x_lib_screens_dukanx_splash_screen_dart", "target": "dukan_x_lib_screens_dukanx_splash_screen_dart_spacer", "relation": "defines", "confidence": "EXTRACTED", "confidence_score": 1.0, "source_file": "Dukan_x\\lib\\screens\\dukanx_splash_screen.dart", "source_location": null, "weight": 1.0}, {"source": "dukan_x_lib_screens_dukanx_splash_screen_dart", "target": "dukan_x_lib_screens_dukanx_splash_screen_dart_sizedbox", "relation": "defines", "confidence": "EXTRACTED", "confidence_score": 1.0, "source_file": "Dukan_x\\lib\\screens\\dukanx_splash_screen.dart", "source_location": null, "weight": 1.0}, {"source": "dukan_x_lib_screens_dukanx_splash_screen_dart", "target": "dukan_x_lib_screens_dukanx_splash_screen_dart_color", "relation": "defines", "confidence": "EXTRACTED", "confidence_score": 1.0, "source_file": "Dukan_x\\lib\\screens\\dukanx_splash_screen.dart", "source_location": null, "weight": 1.0}, {"source": "dukan_x_lib_screens_dukanx_splash_screen_dart", "target": "dukan_x_lib_screens_dukanx_splash_screen_dart_animatedbuilder", "relation": "defines", "confidence": "EXTRACTED", "confidence_score": 1.0, "source_file": "Dukan_x\\lib\\screens\\dukanx_splash_screen.dart", "source_location": null, "weight": 1.0}, {"source": "dukan_x_lib_screens_dukanx_splash_screen_dart", "target": "dukan_x_lib_screens_dukanx_splash_screen_dart_container", "relation": "defines", "confidence": "EXTRACTED", "confidence_score": 1.0, "source_file": "Dukan_x\\lib\\screens\\dukanx_splash_screen.dart", "source_location": null, "weight": 1.0}, {"source": "dukan_x_lib_screens_dukanx_splash_screen_dart", "target": "dukan_x_lib_screens_dukanx_splash_screen_dart_paint", "relation": "defines", "confidence": "EXTRACTED", "confidence_score": 1.0, "source_file": "Dukan_x\\lib\\screens\\dukanx_splash_screen.dart", "source_location": null, "weight": 1.0}, {"source": "dukan_x_lib_screens_dukanx_splash_screen_dart", "target": "dukan_x_lib_screens_dukanx_splash_screen_dart_shouldrepaint", "relation": "defines", "confidence": "EXTRACTED", "confidence_score": 1.0, "source_file": "Dukan_x\\lib\\screens\\dukanx_splash_screen.dart", "source_location": null, "weight": 1.0}, {"source": "dukan_x_lib_screens_dukanx_splash_screen_dart", "target": "dukan_x_lib_screens_dukanx_splash_screen_dart_positioned", "relation": "defines", "confidence": "EXTRACTED", "confidence_score": 1.0, "source_file": "Dukan_x\\lib\\screens\\dukanx_splash_screen.dart", "source_location": null, "weight": 1.0}, {"source": "dukan_x_lib_screens_dukanx_splash_screen_dart", "target": "dart_math", "relation": "imports", "confidence": "EXTRACTED", "confidence_score": 1.0, "source_file": "Dukan_x\\lib\\screens\\dukanx_splash_screen.dart", "source_location": null, "weight": 1.0}, {"source": "dukan_x_lib_screens_dukanx_splash_screen_dart", "target": "package_flutter_material_dart", "relation": "imports", "confidence": "EXTRACTED", "confidence_score": 1.0, "source_file": "Dukan_x\\lib\\screens\\dukanx_splash_screen.dart", "source_location": null, "weight": 1.0}, {"source": "dukan_x_lib_screens_dukanx_splash_screen_dart", "target": "widgets_modern_ui_components_dart", "relation": "imports", "confidence": "EXTRACTED", "confidence_score": 1.0, "source_file": "Dukan_x\\lib\\screens\\dukanx_splash_screen.dart", "source_location": null, "weight": 1.0}, {"source": "dukan_x_lib_screens_dukanx_splash_screen_dart", "target": "core_startup_startup_manager_dart", "relation": "imports", "confidence": "EXTRACTED", "confidence_score": 1.0, "source_file": "Dukan_x\\lib\\screens\\dukanx_splash_screen.dart", "source_location": null, "weight": 1.0}]}