{"nodes": [{"id": "dukan_x_lib_core_session_session_manager_dart", "label": "session_manager.dart", "file_type": "code", "source_file": "Dukan_x\\lib\\core\\session\\session_manager.dart", "source_location": null}, {"id": "dukan_x_lib_core_session_session_manager_dart_usersession", "label": "UserSession", "file_type": "code", "source_file": "Dukan_x\\lib\\core\\session\\session_manager.dart", "source_location": null}, {"id": "dukan_x_lib_core_session_session_manager_dart_sessionmanager", "label": "SessionManager", "file_type": "code", "source_file": "Dukan_x\\lib\\core\\session\\session_manager.dart", "source_location": null}, {"id": "dukan_x_lib_core_session_session_manager_dart_copywith", "label": "copyWith", "file_type": "code", "source_file": "Dukan_x\\lib\\core\\session\\session_manager.dart", "source_location": null}, {"id": "dukan_x_lib_core_session_session_manager_dart_signout", "label": "signOut", "file_type": "code", "source_file": "Dukan_x\\lib\\core\\session\\session_manager.dart", "source_location": null}, {"id": "dukan_x_lib_core_session_session_manager_dart_loadusersession", "label": "_loadUserSession", "file_type": "code", "source_file": "Dukan_x\\lib\\core\\session\\session_manager.dart", "source_location": null}, {"id": "dukan_x_lib_core_session_session_manager_dart_connectwebsocket", "label": "_connectWebSocket", "file_type": "code", "source_file": "Dukan_x\\lib\\core\\session\\session_manager.dart", "source_location": null}, {"id": "dukan_x_lib_core_session_session_manager_dart_cacherole", "label": "_cacheRole", "file_type": "code", "source_file": "Dukan_x\\lib\\core\\session\\session_manager.dart", "source_location": null}, {"id": "dukan_x_lib_core_session_session_manager_dart_updatemetadata", "label": "updateMetadata", "file_type": "code", "source_file": "Dukan_x\\lib\\core\\session\\session_manager.dart", "source_location": null}, {"id": "dukan_x_lib_core_session_session_manager_dart_parsebusinesstype", "label": "_parseBusinessType", "file_type": "code", "source_file": "Dukan_x\\lib\\core\\session\\session_manager.dart", "source_location": null}, {"id": "dukan_x_lib_core_session_session_manager_dart_hasownerpermission", "label": "hasOwnerPermission", "file_type": "code", "source_file": "Dukan_x\\lib\\core\\session\\session_manager.dart", "source_location": null}, {"id": "dukan_x_lib_core_session_session_manager_dart_stateerror", "label": "StateError", "file_type": "code", "source_file": "Dukan_x\\lib\\core\\session\\session_manager.dart", "source_location": null}, {"id": "models_business_type_dart", "label": "../../models/business_type.dart", "file_type": "code", "source_file": "Dukan_x\\lib\\core\\session\\session_manager.dart", "source_location": null}, {"id": "dart_async", "label": "dart:async", "file_type": "code", "source_file": "Dukan_x\\lib\\core\\session\\session_manager.dart", "source_location": null}, {"id": "package_amazon_cognito_identity_dart_2_cognito_dart", "label": "package:amazon_cognito_identity_dart_2/cognito.dart", "file_type": "code", "source_file": "Dukan_x\\lib\\core\\session\\session_manager.dart", "source_location": null}, {"id": "package_dukanx_core_api_api_client_dart", "label": "package:dukanx/core/api/api_client.dart", "file_type": "code", "source_file": "Dukan_x\\lib\\core\\session\\session_manager.dart", "source_location": null}, {"id": "package_flutter_foundation_dart", "label": "package:flutter/foundation.dart", "file_type": "code", "source_file": "Dukan_x\\lib\\core\\session\\session_manager.dart", "source_location": null}, {"id": "package_flutter_secure_storage_flutter_secure_storage_dart", "label": "package:flutter_secure_storage/flutter_secure_storage.dart", "file_type": "code", "source_file": "Dukan_x\\lib\\core\\session\\session_manager.dart", "source_location": null}, {"id": "package_shared_preferences_shared_preferences_dart", "label": "package:shared_preferences/shared_preferences.dart", "file_type": "code", "source_file": "Dukan_x\\lib\\core\\session\\session_manager.dart", "source_location": null}, {"id": "auth_auth_intent_service_dart", "label": "../auth/auth_intent_service.dart", "file_type": "code", "source_file": "Dukan_x\\lib\\core\\session\\session_manager.dart", "source_location": null}, {"id": "services_websocket_service_dart", "label": "../../services/websocket_service.dart", "file_type": "code", "source_file": "Dukan_x\\lib\\core\\session\\session_manager.dart", "source_location": null}], "edges": [{"source": "dukan_x_lib_core_session_session_manager_dart", "target": "dukan_x_lib_core_session_session_manager_dart_usersession", "relation": "defines", "confidence": "EXTRACTED", "confidence_score": 1.0, "source_file": "Dukan_x\\lib\\core\\session\\session_manager.dart", "source_location": null, "weight": 1.0}, {"source": "dukan_x_lib_core_session_session_manager_dart", "target": "dukan_x_lib_core_session_session_manager_dart_sessionmanager", "relation": "defines", "confidence": "EXTRACTED", "confidence_score": 1.0, "source_file": "Dukan_x\\lib\\core\\session\\session_manager.dart", "source_location": null, "weight": 1.0}, {"source": "dukan_x_lib_core_session_session_manager_dart", "target": "dukan_x_lib_core_session_session_manager_dart_copywith", "relation": "defines", "confidence": "EXTRACTED", "confidence_score": 1.0, "source_file": "Dukan_x\\lib\\core\\session\\session_manager.dart", "source_location": null, "weight": 1.0}, {"source": "dukan_x_lib_core_session_session_manager_dart", "target": "dukan_x_lib_core_session_session_manager_dart_signout", "relation": "defines", "confidence": "EXTRACTED", "confidence_score": 1.0, "source_file": "Dukan_x\\lib\\core\\session\\session_manager.dart", "source_location": null, "weight": 1.0}, {"source": "dukan_x_lib_core_session_session_manager_dart", "target": "dukan_x_lib_core_session_session_manager_dart_loadusersession", "relation": "defines", "confidence": "EXTRACTED", "confidence_score": 1.0, "source_file": "Dukan_x\\lib\\core\\session\\session_manager.dart", "source_location": null, "weight": 1.0}, {"source": "dukan_x_lib_core_session_session_manager_dart", "target": "dukan_x_lib_core_session_session_manager_dart_connectwebsocket", "relation": "defines", "confidence": "EXTRACTED", "confidence_score": 1.0, "source_file": "Dukan_x\\lib\\core\\session\\session_manager.dart", "source_location": null, "weight": 1.0}, {"source": "dukan_x_lib_core_session_session_manager_dart", "target": "dukan_x_lib_core_session_session_manager_dart_cacherole", "relation": "defines", "confidence": "EXTRACTED", "confidence_score": 1.0, "source_file": "Dukan_x\\lib\\core\\session\\session_manager.dart", "source_location": null, "weight": 1.0}, {"source": "dukan_x_lib_core_session_session_manager_dart", "target": "dukan_x_lib_core_session_session_manager_dart_updatemetadata", "relation": "defines", "confidence": "EXTRACTED", "confidence_score": 1.0, "source_file": "Dukan_x\\lib\\core\\session\\session_manager.dart", "source_location": null, "weight": 1.0}, {"source": "dukan_x_lib_core_session_session_manager_dart", "target": "dukan_x_lib_core_session_session_manager_dart_parsebusinesstype", "relation": "defines", "confidence": "EXTRACTED", "confidence_score": 1.0, "source_file": "Dukan_x\\lib\\core\\session\\session_manager.dart", "source_location": null, "weight": 1.0}, {"source": "dukan_x_lib_core_session_session_manager_dart", "target": "dukan_x_lib_core_session_session_manager_dart_hasownerpermission", "relation": "defines", "confidence": "EXTRACTED", "confidence_score": 1.0, "source_file": "Dukan_x\\lib\\core\\session\\session_manager.dart", "source_location": null, "weight": 1.0}, {"source": "dukan_x_lib_core_session_session_manager_dart", "target": "dukan_x_lib_core_session_session_manager_dart_stateerror", "relation": "defines", "confidence": "EXTRACTED", "confidence_score": 1.0, "source_file": "Dukan_x\\lib\\core\\session\\session_manager.dart", "source_location": null, "weight": 1.0}, {"source": "dukan_x_lib_core_session_session_manager_dart", "target": "models_business_type_dart", "relation": "imports", "confidence": "EXTRACTED", "confidence_score": 1.0, "source_file": "Dukan_x\\lib\\core\\session\\session_manager.dart", "source_location": null, "weight": 1.0}, {"source": "dukan_x_lib_core_session_session_manager_dart", "target": "dart_async", "relation": "imports", "confidence": "EXTRACTED", "confidence_score": 1.0, "source_file": "Dukan_x\\lib\\core\\session\\session_manager.dart", "source_location": null, "weight": 1.0}, {"source": "dukan_x_lib_core_session_session_manager_dart", "target": "package_amazon_cognito_identity_dart_2_cognito_dart", "relation": "imports", "confidence": "EXTRACTED", "confidence_score": 1.0, "source_file": "Dukan_x\\lib\\core\\session\\session_manager.dart", "source_location": null, "weight": 1.0}, {"source": "dukan_x_lib_core_session_session_manager_dart", "target": "package_dukanx_core_api_api_client_dart", "relation": "imports", "confidence": "EXTRACTED", "confidence_score": 1.0, "source_file": "Dukan_x\\lib\\core\\session\\session_manager.dart", "source_location": null, "weight": 1.0}, {"source": "dukan_x_lib_core_session_session_manager_dart", "target": "package_flutter_foundation_dart", "relation": "imports", "confidence": "EXTRACTED", "confidence_score": 1.0, "source_file": "Dukan_x\\lib\\core\\session\\session_manager.dart", "source_location": null, "weight": 1.0}, {"source": "dukan_x_lib_core_session_session_manager_dart", "target": "package_flutter_secure_storage_flutter_secure_storage_dart", "relation": "imports", "confidence": "EXTRACTED", "confidence_score": 1.0, "source_file": "Dukan_x\\lib\\core\\session\\session_manager.dart", "source_location": null, "weight": 1.0}, {"source": "dukan_x_lib_core_session_session_manager_dart", "target": "package_shared_preferences_shared_preferences_dart", "relation": "imports", "confidence": "EXTRACTED", "confidence_score": 1.0, "source_file": "Dukan_x\\lib\\core\\session\\session_manager.dart", "source_location": null, "weight": 1.0}, {"source": "dukan_x_lib_core_session_session_manager_dart", "target": "auth_auth_intent_service_dart", "relation": "imports", "confidence": "EXTRACTED", "confidence_score": 1.0, "source_file": "Dukan_x\\lib\\core\\session\\session_manager.dart", "source_location": null, "weight": 1.0}, {"source": "dukan_x_lib_core_session_session_manager_dart", "target": "services_websocket_service_dart", "relation": "imports", "confidence": "EXTRACTED", "confidence_score": 1.0, "source_file": "Dukan_x\\lib\\core\\session\\session_manager.dart", "source_location": null, "weight": 1.0}]}